pt_names/__init__.py
pt_names/data_files/__init__.py
pt_names/data_files/first_names.csv
pt_names/data_files/last_names.csv
pt_names/gender_classifier.py
pt_names/pt_name_gen.py
pt_names-0.1.4.dist-info/METADATA
pt_names-0.1.4.dist-info/WHEEL
pt_names-0.1.4.dist-info/RECORD
