Metadata-Version: 2.1
Name: pt-names
Version: 0.1.4
Summary: 
Author: Simao Novais
Author-email: snovaisg.97@gmail.com
Requires-Python: >=3.10,<4.0
Classifier: Programming Language :: Python :: 3
Classifier: Programming Language :: Python :: 3.10
Classifier: Programming Language :: Python :: 3.11
Requires-Dist: importlib-resources (==5.12.0)
Requires-Dist: unidecode (>=1.3.6,<2.0.0)
